odoo/addons/sale_order_weight/README.rst
odoo/addons/sale_order_weight/__init__.py
odoo/addons/sale_order_weight/__manifest__.py
odoo/addons/sale_order_weight/i18n/ca.po
odoo/addons/sale_order_weight/i18n/de.po
odoo/addons/sale_order_weight/i18n/el_GR.po
odoo/addons/sale_order_weight/i18n/es.po
odoo/addons/sale_order_weight/i18n/es_ES.po
odoo/addons/sale_order_weight/i18n/es_VE.po
odoo/addons/sale_order_weight/i18n/fi.po
odoo/addons/sale_order_weight/i18n/fr.po
odoo/addons/sale_order_weight/i18n/hr.po
odoo/addons/sale_order_weight/i18n/hr_HR.po
odoo/addons/sale_order_weight/i18n/hu.po
odoo/addons/sale_order_weight/i18n/id.po
odoo/addons/sale_order_weight/i18n/it.po
odoo/addons/sale_order_weight/i18n/nl.po
odoo/addons/sale_order_weight/i18n/nl_NL.po
odoo/addons/sale_order_weight/i18n/pt.po
odoo/addons/sale_order_weight/i18n/pt_BR.po
odoo/addons/sale_order_weight/i18n/ro.po
odoo/addons/sale_order_weight/i18n/sale_order_weight.pot
odoo/addons/sale_order_weight/i18n/sk.po
odoo/addons/sale_order_weight/i18n/sl.po
odoo/addons/sale_order_weight/i18n/tr.po
odoo/addons/sale_order_weight/i18n/tr_TR.po
odoo/addons/sale_order_weight/i18n/vi_VN.po
odoo/addons/sale_order_weight/i18n/zh_CN.po
odoo/addons/sale_order_weight/models/__init__.py
odoo/addons/sale_order_weight/models/sale_order.py
odoo/addons/sale_order_weight/models/sale_order_line.py
odoo/addons/sale_order_weight/readme/CONTRIBUTORS.rst
odoo/addons/sale_order_weight/readme/DESCRIPTION.rst
odoo/addons/sale_order_weight/readme/USAGE.rst
odoo/addons/sale_order_weight/static/description/icon.png
odoo/addons/sale_order_weight/static/description/index.html
odoo/addons/sale_order_weight/tests/__init__.py
odoo/addons/sale_order_weight/tests/test_sale_order_weight.py
odoo/addons/sale_order_weight/views/sale_report.xml
odoo14_addon_sale_order_weight-14.0.1.0.1.dev8.dist-info/METADATA
odoo14_addon_sale_order_weight-14.0.1.0.1.dev8.dist-info/WHEEL
odoo14_addon_sale_order_weight-14.0.1.0.1.dev8.dist-info/top_level.txt
odoo14_addon_sale_order_weight-14.0.1.0.1.dev8.dist-info/RECORD
