Metadata-Version: 2.1
Name: odoo14-addon-sale-order-weight
Version: 14.0.1.0.1.dev8
Summary: Add products weight in report for sale order
Home-page: https://github.com/OCA/sale-reporting
Author: Apulia Software, Agile Business Group,Odoo Community Association (OCA)
Author-email: support@odoo-community.org
License: GPL-3
Platform: UNKNOWN
Classifier: Programming Language :: Python
Classifier: Framework :: Odoo
Classifier: Framework :: Odoo :: 14.0
Classifier: License :: OSI Approved :: GNU General Public License v3 (GPLv3)
Requires-Python: >=3.6
Requires-Dist: odoo <14.1dev,>=14.0a
